setup.cfg
setup.py
scriptmutex/__init__.py
scriptmutex.egg-info/PKG-INFO
scriptmutex.egg-info/SOURCES.txt
scriptmutex.egg-info/dependency_links.txt
scriptmutex.egg-info/entry_points.txt
scriptmutex.egg-info/not-zip-safe
scriptmutex.egg-info/top_level.txt