Metadata-Version: 1.0
Name: scriptmutex
Version: 0.2dev
Summary: Create a mutex file for use in simple scripts
Home-page: https://github.com/gekitsuu/mutex
Author: Adam Glenn
Author-email: gekitsuu@gmail.com
License: BSD
Keywords: mutex filelock file lock
Platform: UNKNOWN
